odoo/addons/somalimentacio/__init__.py
odoo/addons/somalimentacio/__manifest__.py
odoo/addons/somalimentacio/i18n/ca_ES.po
odoo/addons/somalimentacio/i18n/es.po
odoo/addons/somalimentacio/views/subscription_template.xml
odoo12_addon_somalimentacio-12.0.0.0.1.dist-info/METADATA
odoo12_addon_somalimentacio-12.0.0.0.1.dist-info/WHEEL
odoo12_addon_somalimentacio-12.0.0.0.1.dist-info/top_level.txt
odoo12_addon_somalimentacio-12.0.0.0.1.dist-info/RECORD
